fileformats/extras/vendor/siemens/__init__.py
fileformats/extras/vendor/siemens/_version.py
fileformats/extras/vendor/siemens/medimage.py
fileformats_vendor_siemens_extras-0.2.0.dist-info/METADATA
fileformats_vendor_siemens_extras-0.2.0.dist-info/WHEEL
fileformats_vendor_siemens_extras-0.2.0.dist-info/licenses/LICENSE
fileformats_vendor_siemens_extras-0.2.0.dist-info/RECORD
